{"users": [
{
  "localId": "3bRN1M0H5pbwgQBRx2ZRiIIbw5n1",
  "lastSignedInAt": "1506217571000",
  "createdAt": "1506217571000"
},
{
  "localId": "BB4PT3UdJldjMPH6k7EWTKhtr622",
  "lastSignedInAt": "1506220261000",
  "createdAt": "1506220261000"
},
{
  "localId": "FyOARq8BoCWQ2FwBz2VQ8B2m3wl2",
  "lastSignedInAt": "1506222745000",
  "createdAt": "1506222745000"
},
{
  "localId": "KackwJntjfZ9B3LKLnKN0ptP8Vt2",
  "lastSignedInAt": "1506207824000",
  "createdAt": "1506207824000"
},
{
  "localId": "SOSCDucIibO6yS3DhI4w2u7jn2o2",
  "lastSignedInAt": "1506211452000",
  "createdAt": "1506211452000"
},
{
  "localId": "fjBuPpb6eLRje8CAKiU2lPzk3CI3",
  "lastSignedInAt": "1506237832000",
  "createdAt": "1506237832000"
},
{
  "localId": "gUdOMAWND2eXx3bLpgKPux1V7Ui2",
  "lastSignedInAt": "1506224559000",
  "createdAt": "1506224559000"
},
{
  "localId": "lv9I8eGMyBUIGOEueuoZDbiaoV02",
  "lastSignedInAt": "1506217305000",
  "createdAt": "1506217305000"
},
{
  "localId": "nnZ6Z3ahjoPBxjLY5sb2afySIIh2",
  "lastSignedInAt": "1506216296000",
  "createdAt": "1506216296000"
},
{
  "localId": "tpiEPNrlqwTp0wyIkORZYKUg0862",
  "lastSignedInAt": "1506217370000",
  "createdAt": "1506217370000"
},
{
  "localId": "ztpjSKmsvQNND8c4pB4pOJH9EwO2",
  "lastSignedInAt": "1506217572000",
  "createdAt": "1506217572000"
}]}